charmr/__init__.py
charmr/ai.py
charmr/alias_manager.py
charmr/load_code.py
charmr/main.py
charmr-1.0.11.dist-info/METADATA
charmr-1.0.11.dist-info/WHEEL
charmr-1.0.11.dist-info/entry_points.txt
charmr-1.0.11.dist-info/top_level.txt
charmr-1.0.11.dist-info/RECORD
