Metadata-Version: 2.1
Name: charmr
Version: 1.0.11
Summary: A Magical AI File Converter
Home-page: https://github.com/harlev/charmr
Author: Ron Harlev
Author-email: harlev@gmail.com
License: MIT
Requires-Python: >=3.8
Requires-Dist: openai
Requires-Dist: python-dotenv
